microserial
