Metadata-Version: 2.1
Name: microserial
Version: 1.1.4
Summary: python module for reading data from microbit serial port
Home-page: https://github.com/jenca-adam/microbit/tree/master/microserial/
Author: Adam Jenca
Author-email: jenca.a@gjh.sk
License: UNKNOWN
Platform: UNKNOWN
